[
    {"data":{
       "start":"2003-01-07",
       "end":"2009-01-03",
       "term":"2003-01-07-2009-01-03",
       "state":"SC",
       "type":"sen",
       "party":"Republican"}
    },
    {"data":{
       "district":"3.0",
       "start":"2001-01-03",
       "end":"2003-01-03",
       "term":"2001-01-03-2003-01-03",
       "state":"SC",
       "type":"rep",
       "party":"Republican"}
    },
    {"data":{
       "district":"3.0",
       "start":"1999-01-06",
       "end":"2001-01-03",
       "term":"1999-01-06-2001-01-03",
       "state":"SC",
       "type":"rep",
       "party":"Republican"}
    },
    {"data":{
       "district":"3.0",
       "start":"1997-01-07",
       "end":"1999-01-03",
       "term":"1997-01-07-1999-01-03",
       "state":"SC",
       "type":"rep",
       "party":"Republican"}
    },
    {"data":{
       "district":"3.0",
       "start":"1995-01-04",
       "end":"1997-01-03",
       "term":"1995-01-04-1997-01-03",
       "state":"SC",
       "type":"rep",
       "party":"Republican"}
    }
 ]